{
  "main": {
    "id": "a59f9fe09c6dcc53",
    "type": "split",
    "children": [
      {
        "id": "458159bf227eb0fa",
        "type": "tabs",
        "children": [
          {
            "id": "566a90748f77c816",
            "type": "leaf",
            "state": {
              "type": "empty",
              "state": {}
            }
          }
        ]
      }
    ],
    "direction": "vertical"
  },
  "left": {
    "id": "e6cc91291f35e773",
    "type": "split",
    "children": [
      {
        "id": "e0bd8fb1e3e35d2d",
        "type": "tabs",
        "children": [
          {
            "id": "20b07db93cf062c4",
            "type": "leaf",
            "state": {
              "type": "file-explorer",
              "state": {
                "sortOrder": "alphabetical"
              }
            }
          },
          {
            "id": "2f1fa5a1e3935e99",
            "type": "leaf",
            "state": {
              "type": "search",
              "state": {
                "query": "",
                "matchingCase": false,
                "explainSearch": false,
                "collapseAll": false,
                "extraContext": false,
                "sortOrder": "alphabetical"
              }
            }
          },
          {
            "id": "3ba83e295e072e0e",
            "type": "leaf",
            "state": {
              "type": "starred",
              "state": {}
            }
          }
        ]
      }
    ],
    "direction": "horizontal",
    "width": 300
  },
  "right": {
    "id": "47f9239ca18ad73e",
    "type": "split",
    "children": [
      {
        "id": "80ca5aab95813383",
        "type": "tabs",
        "children": [
          {
            "id": "43c914825cb6f69a",
            "type": "leaf",
            "state": {
              "type": "backlink",
              "state": {
                "collapseAll": false,
                "extraContext": false,
                "sortOrder": "alphabetical",
                "showSearch": false,
                "searchQuery": "",
                "backlinkCollapsed": false,
                "unlinkedCollapsed": true
              }
            }
          },
          {
            "id": "51249fe624698cf6",
            "type": "leaf",
            "state": {
              "type": "outgoing-link",
              "state": {
                "linksCollapsed": false,
                "unlinkedCollapsed": true
              }
            }
          },
          {
            "id": "741affedef210472",
            "type": "leaf",
            "state": {
              "type": "tag",
              "state": {
                "sortOrder": "frequency",
                "useHierarchy": true
              }
            }
          },
          {
            "id": "aa308ff5eba96024",
            "type": "leaf",
            "state": {
              "type": "outline",
              "state": {}
            }
          }
        ]
      }
    ],
    "direction": "horizontal",
    "width": 300,
    "collapsed": true
  },
  "left-ribbon": {
    "hiddenItems": {
      "switcher:Меню быстрого перехода": false,
      "graph:Граф": false,
      "canvas:Create new canvas": false,
      "daily-notes:Сегодняшняя заметка": false,
      "templates:Вставить шаблон": false,
      "command-palette:Открыть палитру команд": false
    }
  },
  "active": "566a90748f77c816",
  "lastOpenFiles": [
    "02 GNU Linux SOFTS.md"
  ]
}